<?xml version="1.0" encoding="UTF-8" standalone="no"?>
<compiereTrl baseLanguage="en_US" language="es_ES" table="AD_ELEMENT" version="">
  <row id="4D0FA90A121E44F3968D9541B5177441" trl="N">
    <value column="Name" isTrl="Y" original="Secundary subCategory">Categoría Secundaria</value>
    <value column="PrintName" isTrl="Y" original="Secundary subCategory">Categoría Secundaria</value>
    <value column="Description" isTrl="N" original=""/>
    <value column="Help" isTrl="N" original=""/>
    <value column="PO_Description" isTrl="N" original=""/>
    <value column="PO_Help" isTrl="N" original=""/>
    <value column="PO_Name" isTrl="N" original=""/>
    <value column="PO_PrintName" isTrl="N" original=""/>
  </row>
  <row id="5C9125D211054100A55210333838409E" trl="N">
    <value column="Name" isTrl="Y" original="SubCategory">Subcategoría</value>
    <value column="PrintName" isTrl="Y" original="SubCategory">Subcategoría</value>
    <value column="Description" isTrl="N" original=""/>
    <value column="Help" isTrl="N" original=""/>
    <value column="PO_Description" isTrl="N" original=""/>
    <value column="PO_Help" isTrl="N" original=""/>
    <value column="PO_Name" isTrl="N" original=""/>
    <value column="PO_PrintName" isTrl="N" original=""/>
  </row>
  <row id="7A53247335354DFFBC9BF27FDD3B458F" trl="N">
    <value column="Name" isTrl="Y" original="Secundary Category">Categoría Secundaria</value>
    <value column="PrintName" isTrl="Y" original="Secundary Category">Categoría Secundaria</value>
    <value column="Description" isTrl="N" original=""/>
    <value column="Help" isTrl="N" original=""/>
    <value column="PO_Description" isTrl="N" original=""/>
    <value column="PO_Help" isTrl="N" original=""/>
    <value column="PO_Name" isTrl="N" original=""/>
    <value column="PO_PrintName" isTrl="N" original=""/>
  </row>
</compiereTrl>
