<?xml version="1.0"?>
  <database name="TABLE SSWH_WITHHOLDINGS_VOIDED">
    <table name="SSWH_WITHHOLDINGS_VOIDED" primaryKey="SSWH_WITHHOLDINGS_VOIDED_KEY">
      <column name="SSWH_WITHHOLDINGS_VOIDED_ID" primaryKey="true" required="true" type="VARCHAR" size="32" autoIncrement="false">
        <default/>
        <onCreateDefault/>
      </column>
      <column name="AD_CLIENT_ID" primaryKey="false" required="true" type="VARCHAR" size="32" autoIncrement="false">
        <default/>
        <onCreateDefault/>
      </column>
      <column name="AD_ORG_ID" primaryKey="false" required="true" type="VARCHAR" size="32" autoIncrement="false">
        <default/>
        <onCreateDefault/>
      </column>
      <column name="CREATED" primaryKey="false" required="true" type="TIMESTAMP" size="7" autoIncrement="false">
        <default><![CDATA[SYSDATE]]></default>
        <onCreateDefault/>
      </column>
      <column name="CREATEDBY" primaryKey="false" required="true" type="VARCHAR" size="32" autoIncrement="false">
        <default/>
        <onCreateDefault/>
      </column>
      <column name="UPDATED" primaryKey="false" required="true" type="TIMESTAMP" size="7" autoIncrement="false">
        <default><![CDATA[SYSDATE]]></default>
        <onCreateDefault/>
      </column>
      <column name="UPDATEDBY" primaryKey="false" required="false" type="VARCHAR" size="32" autoIncrement="false">
        <default/>
        <onCreateDefault/>
      </column>
      <column name="ISACTIVE" primaryKey="false" required="true" type="CHAR" size="1" autoIncrement="false">
        <default><![CDATA[Y]]></default>
        <onCreateDefault/>
      </column>
      <column name="C_DOCTYPE_ID" primaryKey="false" required="true" type="VARCHAR" size="32" autoIncrement="false">
        <default/>
        <onCreateDefault/>
      </column>
      <column name="DOCUMENTNO" primaryKey="false" required="true" type="VARCHAR" size="40" autoIncrement="false">
        <default/>
        <onCreateDefault/>
      </column>
      <column name="WITHHOLDINGDATE" primaryKey="false" required="true" type="TIMESTAMP" size="7" autoIncrement="false">
        <default><![CDATA[SYSDATE]]></default>
        <onCreateDefault/>
      </column>
      <column name="STABLISHMENT" primaryKey="false" required="true" type="VARCHAR" size="10" autoIncrement="false">
        <default/>
        <onCreateDefault/>
      </column>
      <column name="SHELL" primaryKey="false" required="true" type="VARCHAR" size="10" autoIncrement="false">
        <default/>
        <onCreateDefault/>
      </column>
      <column name="REFERENCENO_FROM" primaryKey="false" required="true" type="VARCHAR" size="20" autoIncrement="false">
        <default/>
        <onCreateDefault/>
      </column>
      <column name="REFERENCENO_TO" primaryKey="false" required="true" type="VARCHAR" size="20" autoIncrement="false">
        <default/>
        <onCreateDefault/>
      </column>
      <column name="DESCRIPTION" primaryKey="false" required="false" type="VARCHAR" size="255" autoIncrement="false">
        <default/>
        <onCreateDefault/>
      </column>
      <column name="C_DOCTYPE2_ID" primaryKey="false" required="false" type="VARCHAR" size="32" autoIncrement="false">
        <default/>
        <onCreateDefault/>
      </column>
      <column name="DOC_VOIDED" primaryKey="false" required="true" type="VARCHAR" size="60" autoIncrement="false">
        <default/>
        <onCreateDefault/>
      </column>
      <column name="PROCESSED" primaryKey="false" required="true" type="VARCHAR" size="60" autoIncrement="false">
        <default><![CDATA[N]]></default>
        <onCreateDefault/>
      </column>
      <column name="AUTHORIZATIONNO" primaryKey="false" required="true" type="VARCHAR" size="37" autoIncrement="false">
        <default><![CDATA[1234567890]]></default>
        <onCreateDefault/>
      </column>
      <foreign-key foreignTable="AD_CLIENT" name="SSWH_WITHH_VOID_AD_CLIENT">
        <reference local="AD_CLIENT_ID" foreign="AD_CLIENT_ID"/>
      </foreign-key>
      <foreign-key foreignTable="AD_ORG" name="SSWH_WITHH_VOID_AD_ORG">
        <reference local="AD_ORG_ID" foreign="AD_ORG_ID"/>
      </foreign-key>
      <foreign-key foreignTable="C_DOCTYPE" name="SSWH_WITHH_VOID_C_DOCTYPE">
        <reference local="C_DOCTYPE_ID" foreign="C_DOCTYPE_ID"/>
      </foreign-key>
      <foreign-key foreignTable="C_DOCTYPE" name="SSWH_WITHH_VOID_C_DOCTYPE2">
        <reference local="C_DOCTYPE2_ID" foreign="C_DOCTYPE_ID"/>
      </foreign-key>
      <check name="SSWH_WITHH_V_ISACTIVE_CHK"><![CDATA[ISACTIVE IN ('Y', 'N')]]></check>
    </table>
  </database>
