<?xml version="1.0" encoding="UTF-8" standalone="no"?>
<compiereTrl baseLanguage="en_US" language="es_ES" table="AD_TEXTINTERFACES" version="">
  <row id="131C3AF93FB94790ADF4290BEA5FA581" trl="N">
    <value column="Text" isTrl="N" original="TOTAL INCOME">Total Ingreso</value>
  </row>
  <row id="1E54368A84434ADF8DBC0B9F775B69E3" trl="N">
    <value column="Text" isTrl="N" original="Value">Valor</value>
  </row>
  <row id="2270EBAA352E4EA7B705DDFDD779E517" trl="N">
    <value column="Text" isTrl="N" original="Remuneration">Remuneración</value>
  </row>
  <row id="2A4CB8C7E5074CA299EC7BC56E0FC75A" trl="N">
    <value column="Text" isTrl="N" original="Name">Nomnbre</value>
  </row>
  <row id="2D18EDE821AC47C696FC7EE8D24BB771" trl="N">
    <value column="Text" isTrl="N" original="Age">Año</value>
  </row>
  <row id="3E4DB60EC96846E7B95C95E3CDD730C8" trl="N">
    <value column="Text" isTrl="N" original="Concept">Concepto</value>
  </row>
  <row id="40CAD673C0984412B7E14442F06E0A5D" trl="N">
    <value column="Text" isTrl="N" original="Expense">Gasto</value>
  </row>
  <row id="4937C87E22CA4282866D45769759B6FF" trl="N">
    <value column="Text" isTrl="N" original="Call out response page">Call out response page</value>
  </row>
  <row id="4AF392175AE84C628AD01BF841751370" trl="N">
    <value column="Text" isTrl="N" original="Entry Date">Fecha entrada</value>
  </row>
  <row id="555EFDE117264A379E8B11C2486714CB" trl="N">
    <value column="Text" isTrl="N" original="WORK HISTORY IESS">Historia trabajo IESS</value>
  </row>
  <row id="65488DCD8D294E7DBE7368C63191EB04" trl="N">
    <value column="Text" isTrl="N" original="Income">Ingreso</value>
  </row>
  <row id="6C23A76E39FE47538CE1F2929F27E060" trl="N">
    <value column="Text" isTrl="N" original="Total Income">Total Ingreso</value>
  </row>
  <row id="78B851D6F6894AC19E15A8900CDC50A3" trl="N">
    <value column="Text" isTrl="N" original="Status">Estatus</value>
  </row>
  <row id="970E68902CF54751B17CAEA6A6E5038E" trl="N">
    <value column="Text" isTrl="N" original="TOTAL EXPENSE">Total Gasto</value>
  </row>
  <row id="AB71648713E5423BB143B64A65405E48" trl="N">
    <value column="Text" isTrl="N" original="TOTAL INCOME VS TOTAL EXPENSE">Total Ingreso VS Total Gasto</value>
  </row>
  <row id="B1F9C7A66EBA4E6B92DFA56814372C9E" trl="N">
    <value column="Text" isTrl="N" original="NOMBRE">Nombre</value>
  </row>
  <row id="DE47CDBFF6034D12AD21DF4D6E3E64B5" trl="N">
    <value column="Text" isTrl="N" original="Total Expense">Total Gasto</value>
  </row>
  <row id="E2D3F6930C4D4D21A85D2B55B785CD42" trl="N">
    <value column="Text" isTrl="N" original="Diference">Diferencia</value>
  </row>
  <row id="E89148E2BD114FAAB132935EB8D4A8D0" trl="N">
    <value column="Text" isTrl="N" original="VALUE">Valor</value>
  </row>
  <row id="EE8DC1370C604ABB856EE300A5B5E145" trl="N">
    <value column="Text" isTrl="N" original="Tax">Impuesto</value>
  </row>
  <row id="FD00F8D642EA4CBFA42459F738C19FE2" trl="N">
    <value column="Text" isTrl="N" original="STATUS">Estatus</value>
  </row>
</compiereTrl>
