<?xml version="1.0"?>
  <database name="TABLE SFB_BUDGET_LOG_LINE">
    <table name="SFB_BUDGET_LOG_LINE" primaryKey="SFB_BUDGET_LOG_LINE_KEY">
      <column name="SFB_BUDGET_LOG_LINE_ID" primaryKey="true" required="true" type="VARCHAR" size="32" autoIncrement="false">
        <default/>
        <onCreateDefault/>
      </column>
      <column name="AD_CLIENT_ID" primaryKey="false" required="true" type="VARCHAR" size="32" autoIncrement="false">
        <default/>
        <onCreateDefault/>
      </column>
      <column name="AD_ORG_ID" primaryKey="false" required="true" type="VARCHAR" size="32" autoIncrement="false">
        <default/>
        <onCreateDefault/>
      </column>
      <column name="ISACTIVE" primaryKey="false" required="true" type="CHAR" size="1" autoIncrement="false">
        <default/>
        <onCreateDefault/>
      </column>
      <column name="CREATED" primaryKey="false" required="true" type="TIMESTAMP" size="7" autoIncrement="false">
        <default/>
        <onCreateDefault/>
      </column>
      <column name="CREATEDBY" primaryKey="false" required="true" type="VARCHAR" size="32" autoIncrement="false">
        <default/>
        <onCreateDefault/>
      </column>
      <column name="UPDATED" primaryKey="false" required="true" type="TIMESTAMP" size="7" autoIncrement="false">
        <default/>
        <onCreateDefault/>
      </column>
      <column name="UPDATEDBY" primaryKey="false" required="true" type="VARCHAR" size="32" autoIncrement="false">
        <default/>
        <onCreateDefault/>
      </column>
      <column name="SFB_BUDGET_LINE_ID" primaryKey="false" required="true" type="VARCHAR" size="32" autoIncrement="false">
        <default/>
        <onCreateDefault/>
      </column>
      <column name="LINE" primaryKey="false" required="true" type="DECIMAL" size="10,0" autoIncrement="false">
        <default/>
        <onCreateDefault/>
      </column>
      <column name="JAN_NEWADJUSTED_VALUE" primaryKey="false" required="true" type="DECIMAL" autoIncrement="false">
        <default/>
        <onCreateDefault/>
      </column>
      <column name="FEB_NEWADJUSTED_VALUE" primaryKey="false" required="true" type="DECIMAL" autoIncrement="false">
        <default/>
        <onCreateDefault/>
      </column>
      <column name="MAR_NEWADJUSTED_VALUE" primaryKey="false" required="true" type="DECIMAL" autoIncrement="false">
        <default/>
        <onCreateDefault/>
      </column>
      <column name="APR_NEWADJUSTED_VALUE" primaryKey="false" required="true" type="DECIMAL" autoIncrement="false">
        <default/>
        <onCreateDefault/>
      </column>
      <column name="MAY_NEWADJUSTED_VALUE" primaryKey="false" required="true" type="DECIMAL" autoIncrement="false">
        <default/>
        <onCreateDefault/>
      </column>
      <column name="JUN_NEWADJUSTED_VALUE" primaryKey="false" required="true" type="DECIMAL" autoIncrement="false">
        <default/>
        <onCreateDefault/>
      </column>
      <column name="JUL_NEWADJUSTED_VALUE" primaryKey="false" required="true" type="DECIMAL" autoIncrement="false">
        <default/>
        <onCreateDefault/>
      </column>
      <column name="AUG_NEWADJUSTED_VALUE" primaryKey="false" required="true" type="DECIMAL" autoIncrement="false">
        <default/>
        <onCreateDefault/>
      </column>
      <column name="SEP_NEWADJUSTED_VALUE" primaryKey="false" required="true" type="DECIMAL" autoIncrement="false">
        <default/>
        <onCreateDefault/>
      </column>
      <column name="OCT_NEWADJUSTED_VALUE" primaryKey="false" required="true" type="DECIMAL" autoIncrement="false">
        <default/>
        <onCreateDefault/>
      </column>
      <column name="NOV_NEWADJUSTED_VALUE" primaryKey="false" required="true" type="DECIMAL" autoIncrement="false">
        <default/>
        <onCreateDefault/>
      </column>
      <column name="DEC_NEWADJUSTED_VALUE" primaryKey="false" required="true" type="DECIMAL" autoIncrement="false">
        <default/>
        <onCreateDefault/>
      </column>
      <column name="JAN_ADJUSTED_VALUE" primaryKey="false" required="true" type="DECIMAL" autoIncrement="false">
        <default/>
        <onCreateDefault/>
      </column>
      <column name="FEB_ADJUSTED_VALUE" primaryKey="false" required="true" type="DECIMAL" autoIncrement="false">
        <default/>
        <onCreateDefault/>
      </column>
      <column name="MAR_ADJUSTED_VALUE" primaryKey="false" required="true" type="DECIMAL" autoIncrement="false">
        <default/>
        <onCreateDefault/>
      </column>
      <column name="APR_ADJUSTED_VALUE" primaryKey="false" required="true" type="DECIMAL" autoIncrement="false">
        <default/>
        <onCreateDefault/>
      </column>
      <column name="MAY_ADJUSTED_VALUE" primaryKey="false" required="true" type="DECIMAL" autoIncrement="false">
        <default/>
        <onCreateDefault/>
      </column>
      <column name="JUN_ADJUSTED_VALUE" primaryKey="false" required="true" type="DECIMAL" autoIncrement="false">
        <default/>
        <onCreateDefault/>
      </column>
      <column name="JUL_ADJUSTED_VALUE" primaryKey="false" required="true" type="DECIMAL" autoIncrement="false">
        <default/>
        <onCreateDefault/>
      </column>
      <column name="AUG_ADJUSTED_VALUE" primaryKey="false" required="true" type="DECIMAL" autoIncrement="false">
        <default/>
        <onCreateDefault/>
      </column>
      <column name="SEP_ADJUSTED_VALUE" primaryKey="false" required="true" type="DECIMAL" autoIncrement="false">
        <default/>
        <onCreateDefault/>
      </column>
      <column name="OCT_ADJUSTED_VALUE" primaryKey="false" required="true" type="DECIMAL" autoIncrement="false">
        <default/>
        <onCreateDefault/>
      </column>
      <column name="NOV_ADJUSTED_VALUE" primaryKey="false" required="true" type="DECIMAL" autoIncrement="false">
        <default/>
        <onCreateDefault/>
      </column>
      <column name="DEC_ADJUSTED_VALUE" primaryKey="false" required="true" type="DECIMAL" autoIncrement="false">
        <default/>
        <onCreateDefault/>
      </column>
      <column name="SFB_BUDGET_LOG_ID" primaryKey="false" required="true" type="VARCHAR" size="32" autoIncrement="false">
        <default/>
        <onCreateDefault/>
      </column>
      <column name="DIRECTION" primaryKey="false" required="true" type="VARCHAR" size="60" autoIncrement="false">
        <default/>
        <onCreateDefault/>
      </column>
      <foreign-key foreignTable="AD_CLIENT" name="SFB_BUDGETLOGLINE_AD_CLIENT">
        <reference local="AD_CLIENT_ID" foreign="AD_CLIENT_ID"/>
      </foreign-key>
      <foreign-key foreignTable="AD_ORG" name="SFB_BUDGETLOGLINE_AD_ORG">
        <reference local="AD_ORG_ID" foreign="AD_ORG_ID"/>
      </foreign-key>
      <foreign-key foreignTable="SFB_BUDGET_LINE" name="SFB_BUDGETLOGLINE_BUDGETLINE">
        <reference local="SFB_BUDGET_LINE_ID" foreign="SFB_BUDGET_LINE_ID"/>
      </foreign-key>
      <foreign-key foreignTable="SFB_BUDGET_LOG" name="SFB_BUDGETLOGLINE_BUDGETLOG">
        <reference local="SFB_BUDGET_LOG_ID" foreign="SFB_BUDGET_LOG_ID"/>
      </foreign-key>
      <check name="SFB_BUDGETLOGLINE_ACTIVE_CHK"><![CDATA[ISACTIVE IN ('Y', 'N')]]></check>
    </table>
  </database>
