<?xml version="1.0" encoding="UTF-8" standalone="no"?>
<compiereTrl baseLanguage="en_US" language="es_ES" table="OBUISEL_SELECTOR_FIELD" version="">
  <row id="006D33BB00084AF3AC67A2169F5754D1" trl="N">
    <value column="Name" isTrl="Y" original="vendor">Proveedor</value>
    <value column="Description" isTrl="N" original=""/>
    <value column="Help" isTrl="N" original=""/>
  </row>
  <row id="0E15657638064257AF82C4718EE0623C" trl="N">
    <value column="Name" isTrl="Y" original="Name">Nombre</value>
    <value column="Description" isTrl="N" original=""/>
    <value column="Help" isTrl="N" original=""/>
  </row>
  <row id="35C366856BFE47228CC5383DCFA5ADEC" trl="N">
    <value column="Name" isTrl="Y" original="Name 2">Nombre 2</value>
    <value column="Description" isTrl="N" original=""/>
    <value column="Help" isTrl="N" original=""/>
  </row>
  <row id="411C44E5E44F4583A7E52EFA49FC6BC7" trl="N">
    <value column="Name" isTrl="Y" original="Category">Categoría</value>
    <value column="Description" isTrl="N" original=""/>
    <value column="Help" isTrl="N" original=""/>
  </row>
  <row id="A85938C29BC04C9592C49F1C515DB065" trl="N">
    <value column="Name" isTrl="Y" original="Customer">Cliente</value>
    <value column="Description" isTrl="N" original=""/>
    <value column="Help" isTrl="N" original=""/>
  </row>
  <row id="B949636DCE1D4691BD0B8851B2030A95" trl="N">
    <value column="Name" isTrl="Y" original="Credit Line available">Crédito disponible</value>
    <value column="Description" isTrl="N" original=""/>
    <value column="Help" isTrl="N" original=""/>
  </row>
  <row id="BF12CEE8855C4404B0668298135652F9" trl="N">
    <value column="Name" isTrl="Y" original="Customer Balance">Crédito usado</value>
    <value column="Description" isTrl="N" original=""/>
    <value column="Help" isTrl="N" original=""/>
  </row>
  <row id="C55E984088DA4C2299796548D9C2ED0D" trl="N">
    <value column="Name" isTrl="Y" original="identifier">Identificador</value>
    <value column="Description" isTrl="N" original=""/>
    <value column="Help" isTrl="N" original=""/>
  </row>
  <row id="EB55D771A41E4F798571F6C6E262BA77" trl="N">
    <value column="Name" isTrl="Y" original="Value">Valor</value>
    <value column="Description" isTrl="N" original=""/>
    <value column="Help" isTrl="N" original=""/>
  </row>
  <row id="EDA9BE090E58470687E043BD1CC6B542" trl="N">
    <value column="Name" isTrl="Y" original="taxID">Cédula</value>
    <value column="Description" isTrl="N" original=""/>
    <value column="Help" isTrl="N" original=""/>
  </row>
</compiereTrl>
