<?xml version="1.0"?>
  <database name="TABLE SFPR_EMPLOYEE_SITUATION2">
    <table name="SFPR_EMPLOYEE_SITUATION2" primaryKey="SFPR_EMPLOYEE_SITUATION2_KEY">
      <column name="AD_CLIENT_ID" primaryKey="false" required="false" type="VARCHAR" size="32" autoIncrement="false">
        <default/>
        <onCreateDefault/>
      </column>
      <column name="AD_ORG_ID" primaryKey="false" required="true" type="VARCHAR" size="32" autoIncrement="false">
        <default/>
        <onCreateDefault/>
      </column>
      <column name="CREATED" primaryKey="false" required="true" type="TIMESTAMP" size="7" autoIncrement="false">
        <default><![CDATA[SYSDATE]]></default>
        <onCreateDefault/>
      </column>
      <column name="CREATEDBY" primaryKey="false" required="true" type="VARCHAR" size="32" autoIncrement="false">
        <default/>
        <onCreateDefault/>
      </column>
      <column name="UPDATED" primaryKey="false" required="true" type="TIMESTAMP" size="7" autoIncrement="false">
        <default><![CDATA[SYSDATE]]></default>
        <onCreateDefault/>
      </column>
      <column name="UPDATEDBY" primaryKey="false" required="true" type="VARCHAR" size="32" autoIncrement="false">
        <default/>
        <onCreateDefault/>
      </column>
      <column name="SFPR_EMPLOYEE_SITUATION2_ID" primaryKey="true" required="true" type="VARCHAR" size="32" autoIncrement="false">
        <default/>
        <onCreateDefault/>
      </column>
      <column name="SFPR_ACTION_TYPE_ID" primaryKey="false" required="true" type="VARCHAR" size="32" autoIncrement="false">
        <default/>
        <onCreateDefault/>
      </column>
      <column name="PROPOSAL_RMU" primaryKey="false" required="true" type="DECIMAL" autoIncrement="false">
        <default><![CDATA[0]]></default>
        <onCreateDefault/>
      </column>
      <column name="STARTDATE" primaryKey="false" required="true" type="TIMESTAMP" size="7" autoIncrement="false">
        <default><![CDATA[SYSDATE]]></default>
        <onCreateDefault/>
      </column>
      <column name="ENDDATE" primaryKey="false" required="true" type="TIMESTAMP" size="7" autoIncrement="false">
        <default><![CDATA[SYSDATE]]></default>
        <onCreateDefault/>
      </column>
      <column name="C_COSTCENTER_ID" primaryKey="false" required="true" type="VARCHAR" size="32" autoIncrement="false">
        <default/>
        <onCreateDefault/>
      </column>
      <column name="ISACTIVE" primaryKey="false" required="true" type="CHAR" size="1" autoIncrement="false">
        <default><![CDATA[Y]]></default>
        <onCreateDefault/>
      </column>
      <column name="SFPR_EMPLOYEE_POSITION_ID" primaryKey="false" required="true" type="VARCHAR" size="32" autoIncrement="false">
        <default/>
        <onCreateDefault/>
      </column>
      <foreign-key foreignTable="AD_CLIENT" name="SFPR_ESITUATION2_AD_CLIENT">
        <reference local="AD_CLIENT_ID" foreign="AD_CLIENT_ID"/>
      </foreign-key>
      <foreign-key foreignTable="AD_ORG" name="SFPR_ESITUATION2_AD_ORG">
        <reference local="AD_ORG_ID" foreign="AD_ORG_ID"/>
      </foreign-key>
      <foreign-key foreignTable="SFPR_ACTION_TYPE" name="SFPR_ESITUATION2_ATYPE">
        <reference local="SFPR_ACTION_TYPE_ID" foreign="SFPR_ACTION_TYPE_ID"/>
      </foreign-key>
      <foreign-key foreignTable="C_COSTCENTER" name="SFPR_ESITUATION2_CCENTER">
        <reference local="C_COSTCENTER_ID" foreign="C_COSTCENTER_ID"/>
      </foreign-key>
      <foreign-key foreignTable="SSPR_POSITION" name="SFPR_ESITUATION2_POSITION">
        <reference local="SFPR_EMPLOYEE_POSITION_ID" foreign="SSPR_POSITION_ID"/>
      </foreign-key>
      <check name="SFPR_ESITUATION2_ISACTIVE_CHK"><![CDATA[ISACTIVE IN ('Y', 'N')]]></check>
    </table>
  </database>
