<?xml version="1.0" encoding="UTF-8" standalone="no"?>
<compiereTrl baseLanguage="en_US" language="es_ES" table="AD_FIELD" version="">
  <row id="B6864E0192534E4EAFE71676E13F25E6" trl="N">
    <value column="Name" isTrl="N" original="Empleado">Empleado</value>
    <value column="Description" isTrl="N" original="Persona que participa en operaciones diarias de negocios, como cliente, empleado, etc.">Persona que participa en operaciones diarias de negocios, como cliente, empleado, etc.</value>
    <value column="Help" isTrl="N" original="Un tercero es cualquier entidad, organización o particular&amp;nbsp;con&amp;nbsp;quien se realizan operaciones y&amp;nbsp;transacciones. Esto incluye proveedores, clientes y empleados. ">Un tercero es cualquier entidad, organización o particular&amp;nbsp;con&amp;nbsp;quien se realizan operaciones y&amp;nbsp;transacciones. Esto incluye proveedores, clientes y empleados. </value>
  </row>
</compiereTrl>
